tse_dataloader/__init__.py
tse_dataloader/analysis.py
tse_dataloader/download.py
tse_dataloader/stock_list.py
tse_dataloader-0.1.2.dist-info/LICENSE.txt
tse_dataloader-0.1.2.dist-info/METADATA
tse_dataloader-0.1.2.dist-info/WHEEL
tse_dataloader-0.1.2.dist-info/top_level.txt
tse_dataloader-0.1.2.dist-info/RECORD
