Metadata-Version: 2.1
Name: tse-dataloader
Version: 0.1.2
Summary: Python package for downloading Tehran Stock Exchange data and analysing
Home-page: https://github.com/aliik7/tse_dataloader
Author: Aliik7
Author-email: aliik2@gmail.com
License: UNKNOWN
Platform: UNKNOWN
Classifier: Programming Language :: Python :: 3
Classifier: License :: OSI Approved :: MIT License
Classifier: Operating System :: OS Independent
Requires-Python: >=3.6
Requires-Dist: matplotlib
Requires-Dist: pandas
Requires-Dist: bs4
Requires-Dist: requests
Requires-Dist: jdatetime
